examples/__init__.py
examples/all_the_things.py
examples/checkpoints.py
examples/example_plugs.py
examples/frontend_example.py
examples/hello_world.py
examples/ignore_early_canceled_tests.py
examples/measurements.py
examples/phase_groups.py
examples/repeat.py
examples/stop_on_first_failure.py
examples/with_plugs.py
openhtf/__init__.py
openhtf/core/__init__.py
openhtf/core/base_plugs.py
openhtf/core/diagnoses_lib.py
openhtf/core/measurements.py
openhtf/core/monitors.py
openhtf/core/phase_branches.py
openhtf/core/phase_collections.py
openhtf/core/phase_descriptor.py
openhtf/core/phase_executor.py
openhtf/core/phase_group.py
openhtf/core/phase_nodes.py
openhtf/core/test_descriptor.py
openhtf/core/test_executor.py
openhtf/core/test_record.py
openhtf/core/test_state.py
openhtf/output/__init__.py
openhtf/output/callbacks/__init__.py
openhtf/output/callbacks/console_summary.py
openhtf/output/callbacks/json_factory.py
openhtf/output/callbacks/mfg_inspector.py
openhtf/output/proto/__init__.py
openhtf/output/proto/assembly_event.proto
openhtf/output/proto/assembly_event_pb2.py
openhtf/output/proto/guzzle.proto
openhtf/output/proto/guzzle_pb2.py
openhtf/output/proto/mfg_event.proto
openhtf/output/proto/mfg_event_converter.py
openhtf/output/proto/mfg_event_pb2.py
openhtf/output/proto/test_runs.proto
openhtf/output/proto/test_runs_converter.py
openhtf/output/proto/test_runs_pb2.py
openhtf/output/servers/__init__.py
openhtf/output/servers/dashboard_server.py
openhtf/output/servers/pub_sub.py
openhtf/output/servers/station_server.py
openhtf/output/servers/web_gui_server.py
openhtf/output/web_gui/README.md
openhtf/output/web_gui/__init__.py
openhtf/output/web_gui/package-lock.json
openhtf/output/web_gui/package.json
openhtf/output/web_gui/tsconfig.json
openhtf/output/web_gui/tslint.json
openhtf/output/web_gui/typedoc.json
openhtf/output/web_gui/web_launcher.py
openhtf/output/web_gui/webpack.config.js
openhtf/output/web_gui/dist/index.html
openhtf-1.5.2.dist-info/AUTHORS
openhtf-1.5.2.dist-info/LICENSE
openhtf-1.5.2.dist-info/METADATA
openhtf-1.5.2.dist-info/WHEEL
openhtf-1.5.2.dist-info/top_level.txt
openhtf-1.5.2.dist-info/RECORD
