Metadata-Version: 2.1
Name: openhtf
Version: 1.5.2
Summary: OpenHTF, the open hardware testing framework.
Home-page: https://github.com/google/openhtf
Author: The OpenHTF Authors
Requires-Python: >=3.7
License-File: LICENSE
License-File: AUTHORS
Requires-Dist: attrs (>=19.3.0)
Requires-Dist: colorama (>=0.3.9)
Requires-Dist: contextlib2 (>=0.5.1)
Requires-Dist: inflection
Requires-Dist: google-auth (>=1.34.0)
Requires-Dist: mutablerecords (>=0.4.1)
Requires-Dist: protobuf (>=3.6.0)
Requires-Dist: PyYAML (>=3.13)
Requires-Dist: pyOpenSSL (>=17.1.0)
Requires-Dist: requests (>=2.27.1)
Requires-Dist: sockjs-tornado (>=1.0.3)
Requires-Dist: tornado (<5.0,>=4.3)
Requires-Dist: typing-extensions
Provides-Extra: examples
Requires-Dist: pandas (>=0.22.0) ; extra == 'examples'
Provides-Extra: serial_collection_plug
Requires-Dist: pyserial (>=3.3.0) ; extra == 'serial_collection_plug'
Provides-Extra: update_units
Requires-Dist: xlrd (>=1.0.0) ; extra == 'update_units'
Provides-Extra: usb_plugs
Requires-Dist: libusb1 (>=1.3.0) ; extra == 'usb_plugs'
Requires-Dist: M2Crypto (>=0.22.3) ; extra == 'usb_plugs'
